{"fee": "", "tel": "", "name": "県庁前", "homepage": "", "route": [{"company": "大分バス（株）", "route": "（急行）大在駅前・坂の市・中細・佐賀関"}, {"company": "大分バス（株）", "route": "大在駅前・坂の市・（中細）"}, {"company": "大分バス（株）", "route": "大洲・岩田循環"}, {"company": "大分バス（株）", "route": "大道・羽屋入口・畑中"}, {"company": "大分バス（株）", "route": "大分駅前・NHK・県立図書館"}, {"company": "大分バス（株）", "route": "大分高校・西町・萩原・大分"}, {"company": "大分バス（株）", "route": "南下郡・パークシティ明野・パークプレイス・アクロス前・萩原・大分、萩原・アクロス前・パークプレイス・パークシティ明野・南下郡・大分"}, {"company": "大分バス（株）", "route": "萩原・アクロス前・明野団地（大分高校）、萩原・大分高校・パークシティ明野"}, {"company": "大分バス（株）", "route": "萩原・高城・池の平・アクロス前・パークプレイス"}, {"company": "大分バス（株）", "route": "牧・小池原・一里塚"}, {"company": "大分バス（株）", "route": "柳通り・花高松"}, {"company": "大分バス（株）", "route": "芸術会館入口・岩田循環"}, {"company": "大分バス（株）", "route": "柳通り・花高松・三ツ川、柳通り・海原橋・鶴崎"}, {"company": "大分バス（株）", "route": "柳通り・花高松・天然塚東"}, {"company": "大分バス（株）", "route": "臨海・三佐・鶴崎"}, {"company": "大分交通（株）", "route": "5号地線12"}, {"company": "大分交通（株）", "route": "県立図書館線2"}, {"company": "大分交通（株）", "route": "県立図書館線3"}, {"company": "大分交通（株）", "route": "大洲循環線"}, {"company": "大分バス（株）", "route": "高城・鶴崎・城原"}, {"company": "大分バス（株）", "route": "高城・鶴崎"}, {"company": "大分バス（株）", "route": "高城・鶴崎・丸亀"}, {"company": "大分バス（株）", "route": "高城・鶴崎・大在駅前・横塚東"}, {"company": "大分バス（株）", "route": "高城・別保橋・横尾、高城・別保橋（・皆春団地）・松岡・判田橋"}, {"company": "大分バス（株）", "route": "城崎・花津留（天満宮入口）"}, {"company": "大分バス（株）", "route": "城崎・大津町・大洲運動公園"}], "parking": "", "address": "", "lat": "33.23917817", "lng": "131.6126909", "closingday": "", "open": [{"message": "", "stime": "0:00", "etime": "0:00"}], "thumbnail": "small_busstop.jpg"}