{"fee": "", "tel": "", "name": "第三埠頭入口", "homepage": "", "route": [{"company": "亀の井バス（株）", "route": "海岸経由　鉄輪・観海寺線"}, {"company": "大分交通（株）", "route": "大分・別府・日出～国東"}, {"company": "亀の井バス（株）", "route": "別府湯布院線"}, {"company": "亀の井バス（株）", "route": "くじゅう高原線"}, {"company": "亀の井バス（株）", "route": "外廻り循環線"}, {"company": "大分交通（株）", "route": "APU線50"}, {"company": "大分交通（株）", "route": "APU線52"}, {"company": "大分交通（株）", "route": "APU線AS54"}, {"company": "大分交通（株）", "route": "辻間団地線80"}, {"company": "大分交通（株）", "route": "辻間団地線81"}, {"company": "大分交通（株）", "route": "別大線AS71"}, {"company": "国東観光バス（株）", "route": "国大線、国杵線"}], "parking": "", "address": "", "lat": "33.30100137", "lng": "131.5029908", "closingday": "", "open": [{"message": "", "stime": "0:00", "etime": "0:00"}], "thumbnail": "small_busstop.jpg"}