{"fee": "", "tel": "", "name": "宮崎", "homepage": "", "route": [{"company": "大分バス（株）", "route": "急行・大道・犬飼・野津町・佐伯"}, {"company": "大分バス（株）", "route": "緑が丘・富士見ヶ丘・松が丘大分南高校スクール"}, {"company": "大分バス（株）", "route": "大分臼杵線"}, {"company": "大分バス（株）", "route": "大分臼杵線（大道経由）"}, {"company": "大分バス（株）", "route": "大分～佐伯駅"}, {"company": "大分バス（株）", "route": "大分佐伯線（急行）"}, {"company": "大分バス（株）", "route": "大分～野津町～風連（フウレン）鍾乳洞～佐伯線"}, {"company": "大分バス（株）", "route": "金池～竹田交通（県立病院経由）"}, {"company": "大分バス（株）", "route": "金池～竹田交通（元町経由）"}, {"company": "大分バス（株）", "route": "金池～竹田交通（大道経由）"}, {"company": "大分バス（株）", "route": "犬飼久原～大分"}, {"company": "大分バス（株）", "route": "元町・宮崎・敷戸（星和台）、元町・星和台（大分工業）"}, {"company": "大分バス（株）", "route": "元町・犬飼・田中・竹田"}, {"company": "大分バス（株）", "route": "元町・大分大学入口・戸次"}, {"company": "大分バス（株）", "route": "元町・旦の原・高江ニュータウン（大南団地）"}, {"company": "大分バス（株）", "route": "大道・宮崎・敷戸、大道・星和台（大分工業）"}, {"company": "大分バス（株）", "route": "大道・犬飼・田中・竹田、大道・犬飼・田中"}, {"company": "大分バス（株）", "route": "大道・大分大学入口・戸次、大道・県病入口・榎峠・臼杵"}, {"company": "大分バス（株）", "route": "大道・旦の原・高江ニュータウン（大南団地）"}], "parking": "", "address": "", "lat": "33.19576781", "lng": "131.6100705", "closingday": "", "open": [{"message": "", "stime": "0:00", "etime": "0:00"}], "thumbnail": "small_busstop.jpg"}